{"seed": 902509710, "N": 300, "alive_speed": 0.8136807380584069, "non_threatened_speed": 0.833643046948895, "survivors": [{"index": 96, "speed": 0.8006393629112929, "kill_stats": null}, {"index": 97, "speed": 0.783560690211679, "kill_stats": null}, {"index": 110, "speed": 0.7209377126647848, "kill_stats": null}, {"index": 195, "speed": 0.6946937826333383, "kill_stats": null}, {"index": 210, "speed": 0.5875000400029731, "kill_stats": null}, {"index": 285, "speed": 0.5447539925311827, "kill_stats": null}], "still_alive": [{"index": 18, "speed": 0.868503199133264, "kill_stats": null}, {"index": 39, "speed": 0.9105891670319087, "kill_stats": {"kill_time": 472.36456525657985, "kill_pos": 394.6170784981343, "kill_index": 18}}, {"index": 125, "speed": 0.687651275721277, "kill_stats": null}, {"index": 194, "speed": 0.8550236439236669, "kill_stats": {"kill_time": 477.4872836799032, "kill_pos": 242.38833029801313, "kill_index": 125}}, {"index": 243, "speed": 0.6177969196386823, "kill_stats": {"kill_time": 882.9174288974344, "kill_pos": 395.3390163959405, "kill_index": 210}}, {"index": 246, "speed": 0.5184360426382634, "kill_stats": null}, {"index": 265, "speed": 0.7553460678246418, "kill_stats": {"kill_time": 306.57816792420556, "kill_pos": 31.4059056489013, "kill_index": 246}}, {"index": 284, "speed": 0.6744299649341147, "kill_stats": {"kill_time": 731.2596091743085, "kill_pos": 301.64528253187467, "kill_index": 243}}, {"index": 296, "speed": 0.28065778255367146, "kill_stats": null}, {"index": 299, "speed": 0.29039306407538423, "kill_stats": {"kill_time": 385.48680017965034, "kill_pos": 25.115166906244152, "kill_index": 296}}]}